[
  {
    "id": "2eb1a1e6-9853-47e5-a7e9-f12e4f1a5691",
    "data": [
      {
        "text": "happy morning.",
        "userDefined": false
      }
    ],
    "isTemplate": false,
    "count": 0,
    "lang": "en",
    "updated": 0
  },
  {
    "id": "db6a4e35-e0d9-44e3-989c-42e49da07f5b",
    "data": [
      {
        "text": "good morning.",
        "userDefined": false
      }
    ],
    "isTemplate": false,
    "count": 0,
    "lang": "en",
    "updated": 0
  },
  {
    "id": "5a10f69f-c6f4-40d0-bd93-fcb7645fa98c",
    "data": [
      {
        "text": "hi good morning.",
        "userDefined": false
      }
    ],
    "isTemplate": false,
    "count": 0,
    "lang": "en",
    "updated": 0
  }
]